skryptography/__init__.py
skryptography-1.0.0.dist-info/METADATA
skryptography-1.0.0.dist-info/WHEEL
skryptography-1.0.0.dist-info/entry_points.txt
skryptography-1.0.0.dist-info/RECORD
