Metadata-Version: 2.4
Name: skryptography
Version: 1.0.0
Summary: Add your description here
Author-email: Skanda Bhairava <skandabhairava@gmail.com>
Requires-Python: >=3.13
Requires-Dist: cryptography>=46.0.3
Requires-Dist: elgamal>=0.0.5
Requires-Dist: numpy>=2.3.4
Requires-Dist: pycipher>=0.5.2
Requires-Dist: pycryptodome>=3.23.0
Requires-Dist: pycryptodomex>=3.23.0
